pylfmap/LFmap_healpyFitsConvertorAndGenerator.py
pylfmap/__init__.py
pylfmap/pylfmap.py
pylfmap-0.3.1.dist-info/METADATA
pylfmap-0.3.1.dist-info/WHEEL
pylfmap-0.3.1.dist-info/top_level.txt
pylfmap-0.3.1.dist-info/RECORD
