Metadata-Version: 2.1
Name: pylfmap
Version: 0.3.1
Summary: Python wrapper for LFmap software
Home-page: https://github.com/F-Tomas/pylfmap
Author: Tomas Fodran
Author-email: t.fodran@astro.ru.nl
Requires-Dist: healpy
Requires-Dist: numpy
Requires-Dist: astropy
Requires-Dist: wget
